pyracf/__init__.py
pyracf/getOffsets.py
pyracf/offsets.json
pyracf-0.9.0.dist-info/LICENSE
pyracf-0.9.0.dist-info/METADATA
pyracf-0.9.0.dist-info/WHEEL
pyracf-0.9.0.dist-info/top_level.txt
pyracf-0.9.0.dist-info/RECORD
